{
  "scene_analysis": {
    "scene_type": "car_park",
    "confidence": 0.8620570003986359,
    "places365_predictions": [
      {
        "scene": "parking_lot",
        "confidence": 0.7241140007972717
      },
      {
        "scene": "highway",
        "confidence": 0.10792132467031479
      },
      {
        "scene": "raceway",
        "confidence": 0.09293708205223083
      },
      {
        "scene": "parking_garage/indoor",
        "confidence": 0.013883264735341072
      },
      {
        "scene": "promenade",
        "confidence": 0.006187372840940952
      }
    ],
    "suggested_regions": [
      {
        "region_type": "polygon",
        "coordinates": [
          [
            0.078125,
            0.32708333333333334
          ],
          [
            0.23125,
            0.32708333333333334
          ],
          [
            0.23125,
            0.4395833333333333
          ],
          [
            0.078125,
            0.4395833333333333
          ]
        ],
        "confidence": 0.7,
        "suggested_alert": "vehicle_infringement",
        "alert_config": {
          "detection_type": "vehicle",
          "action": "parking_violation_detection",
          "time_threshold": 300,
          "confidence_threshold": 0.7
        }
      },
      {
        "region_type": "polygon",
        "coordinates": [
          [
            0.23125,
            0.32708333333333334
          ],
          [
            0.3859375,
            0.32708333333333334
          ],
          [
            0.3859375,
            0.4395833333333333
          ],
          [
            0.23125,
            0.4395833333333333
          ]
        ],
        "confidence": 0.7,
        "suggested_alert": "vehicle_infringement",
        "alert_config": {
          "detection_type": "vehicle",
          "action": "parking_violation_detection",
          "time_threshold": 300,
          "confidence_threshold": 0.7
        }
      },
      {
        "region_type": "polygon",
        "coordinates": [
          [
            0.3859375,
            0.32708333333333334
          ],
          [
            0.540625,
            0.32708333333333334
          ],
          [
            0.540625,
            0.4395833333333333
          ],
          [
            0.3859375,
            0.4395833333333333
          ]
        ],
        "confidence": 0.7,
        "suggested_alert": "vehicle_infringement",
        "alert_config": {
          "detection_type": "vehicle",
          "action": "parking_violation_detection",
          "time_threshold": 300,
          "confidence_threshold": 0.7
        }
      },
      {
        "region_type": "polygon",
        "coordinates": [
          [
            0.540625,
            0.32708333333333334
          ],
          [
            0.6953125,
            0.32708333333333334
          ],
          [
            0.6953125,
            0.4395833333333333
          ],
          [
            0.540625,
            0.4395833333333333
          ]
        ],
        "confidence": 0.7,
        "suggested_alert": "vehicle_infringement",
        "alert_config": {
          "detection_type": "vehicle",
          "action": "parking_violation_detection",
          "time_threshold": 300,
          "confidence_threshold": 0.7
        }
      },
      {
        "region_type": "polygon",
        "coordinates": [
          [
            0.6953125,
            0.32708333333333334
          ],
          [
            0.85,
            0.32708333333333334
          ],
          [
            0.85,
            0.4395833333333333
          ],
          [
            0.6953125,
            0.4395833333333333
          ]
        ],
        "confidence": 0.7,
        "suggested_alert": "vehicle_infringement",
        "alert_config": {
          "detection_type": "vehicle",
          "action": "parking_violation_detection",
          "time_threshold": 300,
          "confidence_threshold": 0.7
        }
      }
    ]
  },
  "raw_detections": [
    {
      "class_name": "car",
      "confidence": 0.8744891285896301,
      "bbox": [
        175,
        152,
        320,
        238
      ],
      "center": [
        247,
        195
      ]
    },
    {
      "class_name": "car",
      "confidence": 0.8653998374938965,
      "bbox": [
        68,
        173,
        223,
        269
      ],
      "center": [
        145,
        221
      ]
    },
    {
      "class_name": "car",
      "confidence": 0.8563985824584961,
      "bbox": [
        0,
        195,
        113,
        320
      ],
      "center": [
        56,
        257
      ]
    },
    {
      "class_name": "car",
      "confidence": 0.7652777433395386,
      "bbox": [
        496,
        97,
        604,
        148
      ],
      "center": [
        550,
        122
      ]
    },
    {
      "class_name": "car",
      "confidence": 0.653374433517456,
      "bbox": [
        528,
        82,
        630,
        130
      ],
      "center": [
        579,
        106
      ]
    },
    {
      "class_name": "car",
      "confidence": 0.5900362730026245,
      "bbox": [
        250,
        117,
        442,
        214
      ],
      "center": [
        346,
        166
      ]
    },
    {
      "class_name": "person",
      "confidence": 0.544502854347229,
      "bbox": [
        480,
        106,
        510,
        160
      ],
      "center": [
        495,
        133
      ]
    },
    {
      "class_name": "car",
      "confidence": 0.36673814058303833,
      "bbox": [
        347,
        100,
        504,
        171
      ],
      "center": [
        425,
        135
      ]
    }
  ]
}